{
  "phase": "estimate",
  "pricing_source": {
    "status": "cached"
  },
  "projected_costs": {
    "aws_monthly_premium": 110.0,
    "aws_monthly_balanced": 85.0,
    "aws_monthly_optimized": 62.0
  },
  "complexity_tier": "small",
  "recommendation": {
    "path": "migrate_optimized",
    "path_label": "Migrate optimized",
    "migrate_if": [
      "costs favor AWS"
    ],
    "stay_if": [
      "heavy custom networking"
    ]
  },
  "architecture_comparison": {
    "graviton_monthly": 85.0,
    "x86_equivalent_monthly": 95.0,
    "savings_amount": 10.0,
    "savings_percent": 10.5,
    "note": "Partial Graviton: worker remains x86 (incompatible). Hourly savings only on ready services."
  }
}
